satfarm/SatImage.py
satfarm/__init__.py
satfarm/ops.py
satfarm/utils.py
satfarm/operation/fusion.py
satfarm/processor/__init__.py
satfarm/processor/_advanced_ops.py
satfarm/processor/_attributes.py
satfarm/processor/_basic_ops.py
satfarm/processor/_export.py
satfarm/processor/_io.py
satfarm/processor/_rendering.py
satfarm-0.1.3.dist-info/METADATA
satfarm-0.1.3.dist-info/WHEEL
satfarm-0.1.3.dist-info/licenses/LICENSE
satfarm-0.1.3.dist-info/RECORD
