Metadata-Version: 2.4
Name: satfarm
Version: 0.1.3
Summary: A Python package for satellite image processing with fluent interface
Project-URL: Homepage, https://github.com/saefarm-satellite/satfarm
Project-URL: Repository, https://github.com/saefarm-satellite/satfarm
Project-URL: Documentation, https://github.com/saefarm-satellite/satfarm
Project-URL: Issues, https://github.com/saefarm-satellite/satfarm/issues
Author-email: husgbb <hangm0101@gmail.com>
Maintainer-email: husgbb <hangm0101@gmail.com>
License-Expression: MIT
License-File: LICENSE
Keywords: geospatial,image processing,raster,remote sensing,satellite
Classifier: Development Status :: 3 - Alpha
Classifier: Intended Audience :: Science/Research
Classifier: License :: OSI Approved :: MIT License
Classifier: Operating System :: OS Independent
Classifier: Programming Language :: Python :: 3
Classifier: Programming Language :: Python :: 3.11
Classifier: Programming Language :: Python :: 3.12
Classifier: Topic :: Scientific/Engineering :: GIS
Classifier: Topic :: Scientific/Engineering :: Image Processing
Requires-Python: >=3.11
Requires-Dist: geopandas>=0.12.0
Requires-Dist: matplotlib>=3.5.0
Requires-Dist: numpy>=1.21.0
Requires-Dist: pillow>=9.0.0
Requires-Dist: pytest>=8.0.0
Requires-Dist: rioxarray>=0.13.0
Requires-Dist: typeguard>=4.0.0
Provides-Extra: dev
Requires-Dist: black>=22.0.0; extra == 'dev'
Requires-Dist: flake8>=5.0.0; extra == 'dev'
Requires-Dist: isort>=5.10.0; extra == 'dev'
Requires-Dist: mypy>=1.0.0; extra == 'dev'
Requires-Dist: pytest-cov>=4.0.0; extra == 'dev'
Requires-Dist: pytest>=7.0.0; extra == 'dev'
